changeguard/__init__.py
changeguard/changeguard.py
changeguard/changeguard_test.py
changeguard/cli.py
changeguard-0.3.1.dist-info/LICENSE.md
changeguard-0.3.1.dist-info/METADATA
changeguard-0.3.1.dist-info/WHEEL
changeguard-0.3.1.dist-info/entry_points.txt
changeguard-0.3.1.dist-info/top_level.txt
changeguard-0.3.1.dist-info/RECORD
